lexp/__init__.py
lexp/const.py
lexp/exception.py
lexp/expnode.py
lexp/funcs.py
lexp/util.py
lexp/operation/__init__.py
lexp/operation/binary.py
lexp/operation/bool.py
lexp/operation/custom.py
lexp/operation/ternary.py
lexp/operation/unary.py
lexp-0.1.0.dist-info/LICENSE
lexp-0.1.0.dist-info/METADATA
lexp-0.1.0.dist-info/WHEEL
lexp-0.1.0.dist-info/top_level.txt
lexp-0.1.0.dist-info/RECORD
