Metadata-Version: 2.1
Name: lexp
Version: 0.1.0
Summary: calculate the value of the expression
Home-page: UNKNOWN
Author: Li Zhiyuan
Author-email: nxdlzy@163.com
License: MIT
Platform: UNKNOWN
License-File: LICENSE
